imageruler/__init__.py
imageruler/imageruler.py
imageruler/py.typed
imageruler/regular_shapes.py
imageruler-0.3.0.dist-info/LICENSE.md
imageruler-0.3.0.dist-info/METADATA
imageruler-0.3.0.dist-info/WHEEL
imageruler-0.3.0.dist-info/top_level.txt
imageruler-0.3.0.dist-info/RECORD
