Metadata-Version: 2.1
Name: imageruler
Version: 0.3.0
Summary: Measure minimum sollid/void lengthscales in binary images.
Author: Ian A. D. Williamson, Ardavan Oskooi
Author-email: Wenchao Ma <mawc@mit.edu>, Martin Schubert <mfschubert@gmail.com>, "Steven G. Johnson" <stevenj@mit.edu>
Maintainer: Ian A. D. Williamson, Ardavan Oskooi
Maintainer-email: Wenchao Ma <mawc@mit.edu>, Martin Schubert <mfschubert@gmail.com>, "Steven G. Johnson" <stevenj@mit.edu>
Keywords: topology,optimization,length scale
Requires-Python: >=3.7
License-File: LICENSE.md
Requires-Dist: numpy
Requires-Dist: opencv-python
Provides-Extra: dev
Requires-Dist: bump-my-version ; extra == 'dev'
Requires-Dist: darglint ; extra == 'dev'
Requires-Dist: imageruler[tests] ; extra == 'dev'
Requires-Dist: mypy ; extra == 'dev'
Requires-Dist: pre-commit ; extra == 'dev'
Provides-Extra: docs
Requires-Dist: matplotlib ; extra == 'docs'
Requires-Dist: jupyter-book ; extra == 'docs'
Requires-Dist: scipy ; extra == 'docs'
Requires-Dist: scikit-image ; extra == 'docs'
Requires-Dist: sphinx-autodoc-typehints ; extra == 'docs'
Requires-Dist: sphinx-click ; extra == 'docs'
Provides-Extra: tests
Requires-Dist: parameterized ; extra == 'tests'
Requires-Dist: pytest ; extra == 'tests'
Requires-Dist: pytest-cov ; extra == 'tests'
Requires-Dist: pytest-xdist ; extra == 'tests'
Requires-Dist: scipy ; extra == 'tests'
